pytest_allclose/__init__.py
pytest_allclose/plugin.py
pytest_allclose/version.py
pytest_allclose-1.0.0.dist-info/LICENSE.rst
pytest_allclose-1.0.0.dist-info/METADATA
pytest_allclose-1.0.0.dist-info/WHEEL
pytest_allclose-1.0.0.dist-info/entry_points.txt
pytest_allclose-1.0.0.dist-info/top_level.txt
pytest_allclose-1.0.0.dist-info/RECORD
