Metadata-Version: 2.1
Name: pytest-allclose
Version: 1.0.0
Summary: Pytest fixture extending Numpy's allclose function
Home-page: https://www.nengo.ai/pytest-allclose
Author: Applied Brain Research
Author-email: info@appliedbrainresearch.com
License: MIT license
Platform: UNKNOWN
Classifier: Development Status :: 5 - Production/Stable
Classifier: Framework :: Pytest
Classifier: License :: OSI Approved :: MIT License
Classifier: Programming Language :: Python :: 3 :: Only
Classifier: Programming Language :: Python :: 3.5
Classifier: Programming Language :: Python :: 3.6
Classifier: Programming Language :: Python :: 3.7
Requires-Python: >=3.5
Requires-Dist: numpy (>=1.11)
Requires-Dist: pytest
Provides-Extra: all
Requires-Dist: nengo-sphinx-theme (>=1.0) ; extra == 'all'
Requires-Dist: sphinx ; extra == 'all'
Requires-Dist: codespell ; extra == 'all'
Requires-Dist: coverage (>=4.3) ; extra == 'all'
Requires-Dist: flake8 ; extra == 'all'
Requires-Dist: gitlint ; extra == 'all'
Requires-Dist: pylint ; extra == 'all'
Provides-Extra: docs
Requires-Dist: nengo-sphinx-theme (>=1.0) ; extra == 'docs'
Requires-Dist: sphinx ; extra == 'docs'
Provides-Extra: optional
Provides-Extra: tests
Requires-Dist: codespell ; extra == 'tests'
Requires-Dist: coverage (>=4.3) ; extra == 'tests'
Requires-Dist: flake8 ; extra == 'tests'
Requires-Dist: gitlint ; extra == 'tests'
Requires-Dist: pylint ; extra == 'tests'
